{"openapi":"3.1.0","info":{"title":"OpenAPI definition","version":"v0"},"servers":[{"url":"http://localhost","description":"Generated server url"}],"security":[{"Authorization":[]}],"tags":[{"name":"User Registration","description":"회원가입 신청 목록 조회 및 승인/거부 API"},{"name":"Email Subscription","description":"이메일 수신 설정 API"},{"name":"Translation Task","description":"번역 과제 생성, 조회, 완료 보고 및 성과 보고서 생성 API"},{"name":"Glossary","description":"번역 용어 사전 조회, 추가, 수정, 삭제 및 자동 매핑 API"},{"name":"System Phase","description":"시스템 운영 페이즈 조회 및 전환 API"},{"name":"Kakao Skill","description":"카카오톡 챗봇 스킬 webhook API"},{"name":"User Management","description":"사용자 목록 조회, 휴식 설정, 보정 자수 조정, 관리자 승급/강등 API"},{"name":"Auth","description":"사용자 인증 상태 확인 API"},{"name":"Health","description":"서버 상태 확인 API"}],"paths":{"/glossary/{id}":{"put":{"tags":["Glossary"],"operationId":"update","parameters":[{"name":"id","in":"path","required":true,"schema":{"type":"string","format":"uuid"}}],"requestBody":{"content":{"application/json":{"schema":{"$ref":"#/components/schemas/UpdateRequest"}}},"required":true},"responses":{"200":{"description":"OK","content":{"*/*":{"schema":{"$ref":"#/components/schemas/EntryResponse"}}}}}},"delete":{"tags":["Glossary"],"operationId":"delete","parameters":[{"name":"id","in":"path","required":true,"schema":{"type":"string","format":"uuid"}}],"responses":{"200":{"description":"OK"}}}},"/api/email/subscription/{token}/unsubscribe":{"put":{"tags":["Email Subscription"],"summary":"이메일 수신 거부","description":"이메일 수신을 거부합니다.","operationId":"unsubscribe","parameters":[{"name":"token","in":"path","required":true,"schema":{"type":"string"}}],"responses":{"200":{"description":"OK","content":{"*/*":{"schema":{"$ref":"#/components/schemas/SubscriptionStatusResponse"}}}}}}},"/api/email/subscription/{token}/subscribe":{"put":{"tags":["Email Subscription"],"summary":"이메일 수신 허용","description":"이메일 수신을 허용합니다.","operationId":"subscribe","parameters":[{"name":"token","in":"path","required":true,"schema":{"type":"string"}}],"responses":{"200":{"description":"OK","content":{"*/*":{"schema":{"$ref":"#/components/schemas/SubscriptionStatusResponse"}}}}}}},"/users/{userId}/rest":{"post":{"tags":["User Management"],"operationId":"setRestStatus","parameters":[{"name":"userId","in":"path","required":true,"schema":{"type":"string","format":"uuid"}}],"requestBody":{"content":{"application/json":{"schema":{"$ref":"#/components/schemas/SetRestStatusRequest"}}},"required":true},"responses":{"200":{"description":"OK","content":{"*/*":{"schema":{"$ref":"#/components/schemas/SetRestStatusResponse"}}}}}}},"/users/{userId}/promote":{"post":{"tags":["User Management"],"operationId":"promoteToAdmin","parameters":[{"name":"userId","in":"path","required":true,"schema":{"type":"string","format":"uuid"}}],"responses":{"200":{"description":"OK","content":{"*/*":{"schema":{"$ref":"#/components/schemas/PromoteToAdminResponse"}}}}}}},"/users/{userId}/demote":{"post":{"tags":["User Management"],"operationId":"demoteFromAdmin","parameters":[{"name":"userId","in":"path","required":true,"schema":{"type":"string","format":"uuid"}}],"responses":{"200":{"description":"OK","content":{"*/*":{"schema":{"$ref":"#/components/schemas/DemoteFromAdminResponse"}}}}}}},"/users/{userId}/adjust-char-count":{"post":{"tags":["User Management"],"operationId":"adjustCharCount","parameters":[{"name":"userId","in":"path","required":true,"schema":{"type":"string","format":"uuid"}}],"requestBody":{"content":{"application/json":{"schema":{"$ref":"#/components/schemas/AdjustCharCountRequest"}}},"required":true},"responses":{"200":{"description":"OK","content":{"*/*":{"schema":{"$ref":"#/components/schemas/AdjustCharCountResponse"}}}}}}},"/user/registrations/{id}/rejection":{"post":{"tags":["User Registration"],"operationId":"denyRegistration","parameters":[{"name":"id","in":"path","required":true,"schema":{"type":"string","format":"uuid"}}],"responses":{"200":{"description":"OK"}}}},"/user/registrations/{id}/acceptance":{"post":{"tags":["User Registration"],"operationId":"acceptRegistration","parameters":[{"name":"id","in":"path","required":true,"schema":{"type":"string","format":"uuid"}}],"responses":{"200":{"description":"OK"}}}},"/tasks":{"get":{"tags":["Translation Task"],"operationId":"findAllTasks","parameters":[{"name":"pageable","in":"query","required":true,"schema":{"$ref":"#/components/schemas/Pageable"}}],"responses":{"200":{"description":"OK","content":{"*/*":{"schema":{"$ref":"#/components/schemas/PageTaskSummaryResponse"}}}}}},"post":{"tags":["Translation Task"],"operationId":"createTask","requestBody":{"content":{"application/json":{"schema":{"$ref":"#/components/schemas/CreateTaskRequest"}}},"required":true},"responses":{"200":{"description":"OK","content":{"*/*":{"schema":{"$ref":"#/components/schemas/CreateTaskResponse"}}}}}}},"/tasks/{taskId}/completion":{"post":{"tags":["Translation Task"],"operationId":"reportCompletion","parameters":[{"name":"taskId","in":"path","required":true,"schema":{"type":"string","format":"uuid"}}],"requestBody":{"content":{"application/json":{"schema":{"$ref":"#/components/schemas/ReportCompletionRequest"}}},"required":true},"responses":{"200":{"description":"OK","content":{"*/*":{"schema":{"$ref":"#/components/schemas/ReportCompletionResponse"}}}}}}},"/system-phase/transit":{"post":{"tags":["System Phase"],"operationId":"transitPhase","requestBody":{"content":{"application/json":{"schema":{"$ref":"#/components/schemas/TransitPhaseRequest"}}},"required":true},"responses":{"200":{"description":"OK","content":{"*/*":{"schema":{"$ref":"#/components/schemas/TransitPhaseResponse"}}}}}}},"/glossary":{"get":{"tags":["Glossary"],"operationId":"findAll","parameters":[{"name":"keyword","in":"query","required":false,"schema":{"type":"string"}}],"responses":{"200":{"description":"OK","content":{"*/*":{"schema":{"type":"array","items":{"$ref":"#/components/schemas/EntryResponse"}}}}}}},"post":{"tags":["Glossary"],"operationId":"create","requestBody":{"content":{"application/json":{"schema":{"$ref":"#/components/schemas/CreateRequest"}}},"required":true},"responses":{"200":{"description":"OK","content":{"*/*":{"schema":{"$ref":"#/components/schemas/EntryResponse"}}}}}}},"/glossary/auto-map":{"post":{"tags":["Glossary"],"operationId":"autoMap","requestBody":{"content":{"application/json":{"schema":{"$ref":"#/components/schemas/AutoMapRequest"}}},"required":true},"responses":{"200":{"description":"OK","content":{"*/*":{"schema":{"type":"array","items":{"$ref":"#/components/schemas/AutoMapResponse"}}}}}}}},"/api/kakao/skill":{"post":{"tags":["Kakao Skill"],"operationId":"handleSkill","requestBody":{"content":{"application/json":{"schema":{"$ref":"#/components/schemas/SkillRequest"}}},"required":true},"responses":{"200":{"description":"OK","content":{"*/*":{"schema":{"$ref":"#/components/schemas/SkillResponse"}}}}}}},"/users":{"get":{"tags":["User Management"],"operationId":"findAllUsers","parameters":[{"name":"pageable","in":"query","required":true,"schema":{"$ref":"#/components/schemas/Pageable"}}],"responses":{"200":{"description":"OK","content":{"*/*":{"schema":{"$ref":"#/components/schemas/PageUserSummaryResponse"}}}}}}},"/user/registrations":{"get":{"tags":["User Registration"],"operationId":"findAllRegistrations","parameters":[{"name":"pageable","in":"query","required":true,"schema":{"$ref":"#/components/schemas/Pageable"}}],"responses":{"200":{"description":"OK","content":{"*/*":{"schema":{"$ref":"#/components/schemas/PageRegistrationSummaryResponse"}}}}}}},"/test/security/user":{"get":{"tags":["security-test-controller"],"operationId":"userEndpoint","responses":{"200":{"description":"OK","content":{"*/*":{"schema":{"type":"object","additionalProperties":{"type":"string"}}}}}}}},"/test/security/public":{"get":{"tags":["security-test-controller"],"operationId":"publicEndpoint","responses":{"200":{"description":"OK","content":{"*/*":{"schema":{"type":"object","additionalProperties":{"type":"string"}}}}}}}},"/test/security/kakao":{"get":{"tags":["security-test-controller"],"operationId":"kakaoEndpoint","responses":{"200":{"description":"OK","content":{"*/*":{"schema":{"type":"object","additionalProperties":{"type":"string"}}}}}}}},"/test/security/admin":{"get":{"tags":["security-test-controller"],"operationId":"adminEndpoint","responses":{"200":{"description":"OK","content":{"*/*":{"schema":{"type":"object","additionalProperties":{"type":"string"}}}}}}}},"/test/phase/recruitment-only":{"get":{"tags":["test-phase-controller"],"operationId":"recruitmentOnly","responses":{"200":{"description":"OK","content":{"*/*":{"schema":{"type":"object","additionalProperties":{"type":"string"}}}}}}}},"/test/phase/multiple-phases":{"get":{"tags":["test-phase-controller"],"operationId":"multiplePhases","responses":{"200":{"description":"OK","content":{"*/*":{"schema":{"type":"object","additionalProperties":{"type":"string"}}}}}}}},"/test/phase/deactivation-only":{"get":{"tags":["test-phase-controller"],"operationId":"deactivationOnly","responses":{"200":{"description":"OK","content":{"*/*":{"schema":{"type":"object","additionalProperties":{"type":"string"}}}}}}}},"/tasks/reports/performance.csv":{"get":{"tags":["Translation Task"],"operationId":"generatePerformanceReport","responses":{"200":{"description":"OK","content":{"text/csv;charset=UTF-8":{"schema":{"type":"string"}},"text/csv; charset=UTF-8":{"schema":{"type":"string"}}}}}}},"/system-phase":{"get":{"tags":["System Phase"],"operationId":"getCurrentPhase","responses":{"200":{"description":"OK","content":{"*/*":{"schema":{"$ref":"#/components/schemas/GetCurrentPhaseResponse"}}}}}}},"/health":{"get":{"tags":["Health"],"operationId":"health","responses":{"200":{"description":"OK","content":{"*/*":{"schema":{"type":"string"}}}}}}},"/auth/check":{"get":{"tags":["Auth"],"operationId":"identityCheck","responses":{"200":{"description":"OK","content":{"*/*":{"schema":{"type":"string"}}}}}}},"/api/email/subscription/{token}/status":{"get":{"tags":["Email Subscription"],"summary":"이메일 수신 상태 조회","description":"토큰으로 이메일 수신 상태를 조회합니다.","operationId":"getSubscriptionStatus","parameters":[{"name":"token","in":"path","required":true,"schema":{"type":"string"}}],"responses":{"200":{"description":"OK","content":{"*/*":{"schema":{"$ref":"#/components/schemas/SubscriptionStatusResponse"}}}}}}}},"components":{"schemas":{"UpdateRequest":{"type":"object","properties":{"koreanTerm":{"type":"string"},"englishTerm":{"type":"string"}}},"EntryResponse":{"type":"object","properties":{"id":{"type":"string","format":"uuid"},"koreanTerm":{"type":"string"},"englishTerm":{"type":"string"}}},"SubscriptionStatusResponse":{"type":"object","properties":{"email":{"type":"string"},"subscribed":{"type":"boolean"}}},"SetRestStatusRequest":{"type":"object","properties":{"resting":{"type":"boolean"}}},"SetRestStatusResponse":{"type":"object","properties":{"userId":{"type":"string","format":"uuid"},"resting":{"type":"boolean"}}},"PromoteToAdminResponse":{"type":"object","properties":{"userId":{"type":"string","format":"uuid"},"role":{"type":"string","enum":["STUDENT","ADMIN"]}}},"DemoteFromAdminResponse":{"type":"object","properties":{"userId":{"type":"string","format":"uuid"},"role":{"type":"string","enum":["STUDENT","ADMIN"]}}},"AdjustCharCountRequest":{"type":"object","properties":{"amount":{"type":"integer","format":"int32"}}},"AdjustCharCountResponse":{"type":"object","properties":{"userId":{"type":"string","format":"uuid"},"amount":{"type":"integer","format":"int32"},"adjustedCharCount":{"type":"integer","format":"int32"}}},"CreateTaskRequest":{"type":"object","properties":{"taskType":{"type":"string","enum":["GAONNURI_POST","EXTERNAL_POST"]},"taskDescription":{"type":"string"},"assignmentType":{"type":"string","enum":["AUTOMATIC","MANUAL"]},"assigneeId":{"type":"string","format":"uuid"}}},"CreateTaskResponse":{"type":"object","properties":{"taskId":{"type":"string","format":"uuid"},"assigneeId":{"type":"string","format":"uuid"},"assigneeStudentNumber":{"type":"string"},"assigneeName":{"type":"string"}}},"ReportCompletionRequest":{"type":"object","properties":{"characterCount":{"type":"integer","format":"int32"}}},"ReportCompletionResponse":{"type":"object","properties":{"taskId":{"type":"string","format":"uuid"},"late":{"type":"boolean"}}},"TransitPhaseRequest":{"type":"object","properties":{"nextPhase":{"type":"string","enum":["DEACTIVATION","RECRUITMENT","TRANSLATION","SETTLEMENT"]}}},"TransitPhaseResponse":{"type":"object","properties":{"previousPhase":{"type":"string","enum":["DEACTIVATION","RECRUITMENT","TRANSLATION","SETTLEMENT"]},"currentPhase":{"type":"string","enum":["DEACTIVATION","RECRUITMENT","TRANSLATION","SETTLEMENT"]}}},"CreateRequest":{"type":"object","properties":{"koreanTerm":{"type":"string"},"englishTerm":{"type":"string"}}},"AutoMapRequest":{"type":"object","properties":{"text":{"type":"string"}}},"AutoMapResponse":{"type":"object","properties":{"koreanTerm":{"type":"string"},"englishTerm":{"type":"string"}}},"Action":{"type":"object","properties":{"detailParams":{"type":"object","additionalProperties":{"$ref":"#/components/schemas/DetailParam"}}}},"DetailParam":{"type":"object","properties":{"origin":{"type":"string"},"value":{"type":"string"},"groupName":{"type":"string"}}},"Properties":{"type":"object","properties":{"plusfriendUserKey":{"type":"string"}}},"SkillRequest":{"type":"object","properties":{"action":{"$ref":"#/components/schemas/Action"},"userRequest":{"$ref":"#/components/schemas/UserRequest"}}},"User":{"type":"object","properties":{"properties":{"$ref":"#/components/schemas/Properties"}}},"UserRequest":{"type":"object","properties":{"user":{"$ref":"#/components/schemas/User"}}},"Output":{"type":"object","properties":{"simpleText":{"$ref":"#/components/schemas/SimpleText"}}},"QuickReply":{"type":"object","properties":{"label":{"type":"string"},"action":{"type":"string"},"messageText":{"type":"string"}}},"SimpleText":{"type":"object","properties":{"text":{"type":"string"}}},"SkillResponse":{"type":"object","properties":{"version":{"type":"string"},"template":{"$ref":"#/components/schemas/Template"}}},"Template":{"type":"object","properties":{"outputs":{"type":"array","items":{"$ref":"#/components/schemas/Output"}},"quickReplies":{"type":"array","items":{"$ref":"#/components/schemas/QuickReply"}}}},"Pageable":{"type":"object","properties":{"page":{"type":"integer","format":"int32","minimum":0},"size":{"type":"integer","format":"int32","minimum":1},"sort":{"type":"array","items":{"type":"string"}}}},"PageUserSummaryResponse":{"type":"object","properties":{"totalElements":{"type":"integer","format":"int64"},"totalPages":{"type":"integer","format":"int32"},"size":{"type":"integer","format":"int32"},"content":{"type":"array","items":{"$ref":"#/components/schemas/UserSummaryResponse"}},"number":{"type":"integer","format":"int32"},"first":{"type":"boolean"},"last":{"type":"boolean"},"sort":{"$ref":"#/components/schemas/SortObject"},"numberOfElements":{"type":"integer","format":"int32"},"pageable":{"$ref":"#/components/schemas/PageableObject"},"empty":{"type":"boolean"}}},"PageableObject":{"type":"object","properties":{"offset":{"type":"integer","format":"int64"},"sort":{"$ref":"#/components/schemas/SortObject"},"paged":{"type":"boolean"},"pageNumber":{"type":"integer","format":"int32"},"pageSize":{"type":"integer","format":"int32"},"unpaged":{"type":"boolean"}}},"SortObject":{"type":"object","properties":{"empty":{"type":"boolean"},"sorted":{"type":"boolean"},"unsorted":{"type":"boolean"}}},"UserSummaryResponse":{"type":"object","properties":{"id":{"type":"string","format":"uuid"},"studentNumber":{"type":"string"},"studentName":{"type":"string"},"role":{"type":"string","enum":["STUDENT","ADMIN"]},"warningCount":{"type":"integer","format":"int32"},"adjustedCharCount":{"type":"integer","format":"int32"},"resting":{"type":"boolean"}}},"PageRegistrationSummaryResponse":{"type":"object","properties":{"totalElements":{"type":"integer","format":"int64"},"totalPages":{"type":"integer","format":"int32"},"size":{"type":"integer","format":"int32"},"content":{"type":"array","items":{"$ref":"#/components/schemas/RegistrationSummaryResponse"}},"number":{"type":"integer","format":"int32"},"first":{"type":"boolean"},"last":{"type":"boolean"},"sort":{"$ref":"#/components/schemas/SortObject"},"numberOfElements":{"type":"integer","format":"int32"},"pageable":{"$ref":"#/components/schemas/PageableObject"},"empty":{"type":"boolean"}}},"RegistrationSummaryResponse":{"type":"object","properties":{"id":{"type":"string","format":"uuid"},"studentNumber":{"type":"string"},"studentName":{"type":"string"}}},"PageTaskSummaryResponse":{"type":"object","properties":{"totalElements":{"type":"integer","format":"int64"},"totalPages":{"type":"integer","format":"int32"},"size":{"type":"integer","format":"int32"},"content":{"type":"array","items":{"$ref":"#/components/schemas/TaskSummaryResponse"}},"number":{"type":"integer","format":"int32"},"first":{"type":"boolean"},"last":{"type":"boolean"},"sort":{"$ref":"#/components/schemas/SortObject"},"numberOfElements":{"type":"integer","format":"int32"},"pageable":{"$ref":"#/components/schemas/PageableObject"},"empty":{"type":"boolean"}}},"TaskSummaryResponse":{"type":"object","properties":{"id":{"type":"string","format":"uuid"},"taskType":{"type":"string","enum":["GAONNURI_POST","EXTERNAL_POST"]},"taskDescription":{"type":"string"},"assigneeId":{"type":"string","format":"uuid"},"assigneeStudentNumber":{"type":"string"},"assigneeName":{"type":"string"},"assignmentType":{"type":"string","enum":["AUTOMATIC","MANUAL"]},"assignedAt":{"type":"string"},"characterCount":{"type":"integer","format":"int32"},"completed":{"type":"boolean"}}},"GetCurrentPhaseResponse":{"type":"object","properties":{"currentPhase":{"type":"string","enum":["DEACTIVATION","RECRUITMENT","TRANSLATION","SETTLEMENT"]},"currentPhaseDisplayName":{"type":"string"},"nextPhase":{"type":"string","enum":["DEACTIVATION","RECRUITMENT","TRANSLATION","SETTLEMENT"]},"nextPhaseDisplayName":{"type":"string"}}}},"securitySchemes":{"Authorization":{"type":"apiKey","description":"인증 토큰을 입력하세요. 형식: `user {uuid}` 또는 `kakao {token}`","name":"Authorization","in":"header"}}}}